py_image_dedup/__init__.py
py_image_dedup/cli.py
py_image_dedup/config.py
py_image_dedup/stats.py
py_image_dedup/library/__init__.py
py_image_dedup/library/deduplication_result.py
py_image_dedup/library/deduplicator.py
py_image_dedup/library/file_watch.py
py_image_dedup/library/processing_manager.py
py_image_dedup/library/progress_manager.py
py_image_dedup/persistence/__init__.py
py_image_dedup/persistence/elasticsearchstorebackend.py
py_image_dedup/persistence/metadata_key.py
py_image_dedup/util/__init__.py
py_image_dedup/util/file.py
py_image_dedup/util/image.py
tests/__init__.py
tests/test_file_extension.py
tests/test_select_images_to_delete.py
py_image_dedup-2.0.0.dist-info/LICENSE
py_image_dedup-2.0.0.dist-info/METADATA
py_image_dedup-2.0.0.dist-info/WHEEL
py_image_dedup-2.0.0.dist-info/entry_points.txt
py_image_dedup-2.0.0.dist-info/top_level.txt
py_image_dedup-2.0.0.dist-info/RECORD
