Metadata-Version: 2.1
Name: py-image-dedup
Version: 2.0.0
Summary: A library to find duplicate images and delete unwanted ones
Home-page: https://github.com/markusressel/py-image-dedup
Author: Markus Ressel
Author-email: mail@markusressel.de
License: GPLv3+
Platform: UNKNOWN
Classifier: Development Status :: 5 - Production/Stable
Classifier: License :: OSI Approved :: GNU General Public License v3 or later (GPLv3+)
Classifier: Programming Language :: Python :: 3
Classifier: Programming Language :: Python :: 3.7
Classifier: Programming Language :: Python :: 3.8
Requires-Dist: certifi (==2020.6.20)
Requires-Dist: chardet (==3.0.4)
Requires-Dist: click (==7.1.2)
Requires-Dist: container-app-conf (==5.1.0)
Requires-Dist: cycler (==0.10.0)
Requires-Dist: decorator (==4.4.2)
Requires-Dist: elasticsearch (==7.9.1)
Requires-Dist: idna (==2.10)
Requires-Dist: image-match
Requires-Dist: imageio (==2.9.0)
Requires-Dist: kiwisolver (==1.2.0)
Requires-Dist: matplotlib (==3.3.2)
Requires-Dist: networkx (==2.5)
Requires-Dist: numpy (==1.19.2)
Requires-Dist: ordered-set (==4.0.2)
Requires-Dist: pathtools (==0.1.2)
Requires-Dist: pillow (==7.2.0)
Requires-Dist: prometheus-client (==0.8.0)
Requires-Dist: py-range-parse (==1.0.5)
Requires-Dist: pyparsing (==2.4.7)
Requires-Dist: python-dateutil (==2.8.1)
Requires-Dist: pytimeparse (==1.1.8)
Requires-Dist: pywavelets (==1.1.1)
Requires-Dist: requests (==2.24.0)
Requires-Dist: ruamel.yaml (==0.16.10)
Requires-Dist: ruamel.yaml.clib (==0.2.0)
Requires-Dist: scikit-image (==0.17.2)
Requires-Dist: scipy (==1.5.2)
Requires-Dist: six (==1.15.0)
Requires-Dist: tabulate (==0.8.7)
Requires-Dist: tifffile (==2020.10.1)
Requires-Dist: toml (==0.10.0)
Requires-Dist: tqdm (==4.50.1)
Requires-Dist: urllib3 (==1.25.10)
Requires-Dist: watchdog (==0.10.3)
